{
"2x3rr32ren553plxnrvtcym3":["vtcodes","vt 👨🏿‍💻"],
"wd5ooh7v4totvfdkvzjglfzs":["vtchalakov","Velin"],
"wi6h6dczb7cc5iumzgtx7vo7":["vtclassicist","Cole M Smith"],
"mzwgprvdr2zyjwbfnzixyh7p":["vtc","Vincent"],
"4ruaunq2cskdpqocwejcb5qo":["vtcoolman","The Honorable VT Coolman"],
"mfgirjexz5gql5tycmnqs2wx":["vtcabbit","volt, the cabbit"],
"u5hdls75akbyz3osxwhlqtha":"vtchill",
"ykgutzo7naw3jbph45dvk5e4":"vtclare",
"tin5vw4fuazwpb43ja3zpv5b":["vtcvnz","BEHAPPY"],
"hbrvcvl2rqycqmp4xzz4ghrq":["vtcarmine","Carmine"],
"bprc6ghjn67xh3k6y6fs5xsi":"vtcampos"
}
