{
"7r3idnjt4dz2xib7gv5ioc2k":"0viken0",
"lcwborzszi5biauehd32cnia":["abstrakcija","vika"],
"6szvthrabmq3of6qaaeugzom":["abhayvikram","Abhay Vikram"],
"e2ri6szf7y33frx2q2ugopyb":["adrianviktorb","Adrian Viktor"],
"eojiqndjxoj53ryf6htcl5oe":["adrianviken","Adrian Viken"],
"6gru2vljmh6qvxqwxu3sifta":["ahlqvistviktor","Viktor H. Ahlqvist"],
"zcaazv7bmj5dp4wumgk6bt7z":["airbauer","Viktor"],
"bnak22t2wtahte4oxsukllqj":["alittleredpanda","viki"],
"qq5xsrbhdmf4mj3fywhrcdrn":["antonvikingua.vol.army","Boroda_Viking_Ruda"],
"gypsdjkqdhtsohbkmhi2wmuu":["andreasviking","Andreas Viking"],
"5ctlsmzqb7zgls24flifeitf":["angryvikingpress","Angry Viking Press"],
"w5knpbxqkz4xrrmv3qvakucj":["andrevik","André Heie Vik"],
"y3v6c34krq75fdma7fp4haw2":["andreavik","Andrea Vik"],
"lpvdpyusgqquarjxwvg3zqzv":["artbyvikram","Vikram Madan"],
"re2nyao3uvomvl35k3kujxlj":["artvikkyfoto","Vikky🤍"],
"5ey4nfuo73h62in6u3mbdedn":["arcticursine","Chief Researcher Viktor"],
"r57thtdo42w2ouvrf2dt2eem":["arkastadt","Vikkie 🍄"],
"33pwbudmx7nasj3337pvy2oc":["ashleygjovik","Ashley M. Gjøvik"],
"q7d6nruqlqcfx2souw2bqaqd":["asgardianviking","Space Viking"],
"cfcyefacig3ojakejvyaodsw":["barbarufa","Viking le François "],
"uv2ovisqvgowectdurzjieku":["basquechiguire","Basque Viking Chigüire Fella"],
"giszqfvemttisltnzd3zoqgf":["beardieviking","Beardie_Viking"],
"jsjnwv2p4epuxdxpxq5wngyj":["berduxa","Vika"],
"ee7eo67qpfwact5b5waia4ga":["bigviking","BigViking"],
"orzviv6okg4jjtdma7vhsovx":["bjorkole","Ole Håvik Bjørkedal"],
"f4ys2h5vzpivi35l6wfwqaz2":["bluebery","viktor"],
"vz2atefetatysgbkejtgfaq2":["bookyvikki","Vikki Reilly "],
"z4fq5kgsr2rjpuidkrpvnktp":["brams884","Viktoriia Grivina"],
"abpss4ag6jxteoa7ilkslexk":["butchclown21","Nonbinary Viking"],
"pmnxcuwncowgyfdc5rfvw2tg":["cfsky","Viking©️"],
"yj6vmry46tspiqauok5wnxwi":["chefdad17","VikingWarrior"],
"dzpuy3lebwan5254yk7grwtk":["chtimimie","viki"],
"ypp3wvi5didagfs4pjtzwz6h":["ciaraerenai","Viktor Is Writing a DnD Campaign"],
"j3fhuodwuxc7agrtuajozzw3":["cosmiceclipse","Vikky"],
"rdekxv5muq5accfbtllrpifc":["completeviktory","Viktor"],
"xaaaaazcq4mhg7hs3bnapwvo":["colognaviktoria","Viktoria Cologna"],
"tmu2dlwxd363lypnuxfyrevr":"coco-vikou",
"6spqcv4bdkrxmljiif3l26hn":["cppvik","Viktor ויקטור"],
"v4uj7imbvhskkqype6qodzzo":["crewmansix","Crewman Six, Snack Viking"],
"odkbhbdaniymr2zdamddn6cm":["cvuk","CyberVikingUK"],
"bmybjwjmpx5vxuqp3oig5s2k":["devilmaylove","Featuring Vik From the Devil May Cry series"],
"azjkw4blaeozsh3hctrpgmyt":["disobedienttt","Viktor"],
"f5gm4pi4tsjzvfswk2fkzfqo":["dogzrot","DogzRot (Viktor Vince Roe) ΘΔ 🔜 ANW "],
"qgy7vt74xmouisyslwm3fgfj":["dovgonosyk","Viktor Dovgonosyk🤥🇺🇦"],
"76vux34ewlcx32yetg6drpab":["doyouyearn","vik"],
"vj3ou4edcka2gnm3xhxfuyl7":["ellieraart","Viktoria (Elliera)"],
"ixxoqzofpuoloq6onxekg7qf":["eldritchpervviktor","Viktor"],
"34pecybizvrkzxzauuzno4lg":["enbacka","Viktor Enbacka"],
"l4hdh25y5orkug527idxebim":["enkstheviking","Enks, the Viking"],
"us6uhvixt7cvlkvcxldrot5f":["eulenkueki","Vika "],
"mbbtg6iqbokyoxvicjjyalln":["eviktor","EkoViktor "],
"2jukg3q47womdrkizidqbxlp":["evidence","Ivan Viktor"],
"mm2mvedi3pgijrlrqidmpjfg":["fauxbeatpoet","Vikram Murthi"],
"vq2g7gzbgeewdct3bsmmf4yn":["faroval.fursona.club","Farin Vikka 🔜 ANW"],
"egahu6bxrge6cjyx3llp4uxh":["fatfoxcoon","Vikie Foxfang"],
"wytgupbfyjlbk7zvj5mujyzp":["fagotto","viktor"],
"yivxeucs2xnxolzxmpp3tpv6":["fer0x","Viktor Havrylin"],
"4ul3366fzfmezlzhzvepylih":["fernschild","Ms. Vikki"],
"vewtxwpt25w4o443pe32zaxy":["fetsch","Viktor Fetsch"],
"eaob6gxtghuhlld7jfnztvdd":["fellaviking","VikingFella 🇳🇴🇺🇦✚"],
"u4fzh3jb6v54atwp63hhpypz":["fightyoursorrow","vik @ Fall of Eregion Ch. 1 Coming Soon☆"],
"sme7avomf4ugwzgjcigi6fdr":["firehusky","Viktor"],
"rgaldecmlmncsbwbopfahbjl":["freakkybbygirl","Spookky Vikky 🔞🩸👻"],
"2owk7mvvuv5l4gzm2wph6qbm":["freyatheviking","Freya the Viking (She/They)"],
"giyukciktnm5lpx4n5b54unq":["freyaallmother","Freya | GobboViking"],
"6v3kx23n4eivuqfsjsz5etkq":["furryviking","FurryViking"],
"4lpc4pyf6jifowb5hd2lis3l":["gadeviksand","Sindre Gade Viksand"],
"etrvslq525spcj37w6sjro7k":["gamussa","Viktor Gamov"],
"tjphtgjgznqaf23miccuuphc":["galloviking","GalloViking"],
"nihwhkvqqessoxdnse72dkbx":["gingerviktor","Ginger Viktor"],
"b24emjtaf3wddclwe342sbfm":["gkzr","Viktor Kurochkin"],
"n3biilyekxvni6wsniqxj5ux":["goldenhelikaon","Vik"],
"3nain5osgm43ajz52ktndx3c":["gruzovik373","пан Viktor 🇺🇦"],
"qyvkmotpfaa6pcbf37ne5be2":["grauesuppe","Viktoria Knoll"],
"26xvxmuywl53kbpfc555zynv":["guriiv","Guri Idsø Viken"],
"y6kxsaetjbgfiuwtgxct4ks5":["gunnar.inge.sort.land","Gunnar Inge Gjøvik Sortland"],
"yepjlfhdh7qyimxg7n3hnoei":["gurthorc","Vikingo Jodar "],
"nhhosrgytdpg6hlybpnq77eo":["hailmarys","VIKTOR MEOWFREAK "],
"74jkilhqzriwouma3wk3zlgf":["hefesto-the-viking","Viking Boi"],
"h7vbhvda4lkv2wlnhkvkrafz":["himbo-supreme","Vik Rachman"],
"xlmoczyy43cmawazdnnbru4z":["hntv","Viktor Hnativ"],
"iapxlkogmajo5wbhinasea52":["iblali","Vik"],
"tqs76gy44y57psv2tzxb45hz":["icelandgoddess","VikingGoddess"],
"v6t3a524ahazxy3hpgu72nzp":["ilovemainz","Mainz & Vikings"],
"eh2fs56w4lo4qhrhj4zrwnsh":["ingwazviking","Viking"],
"yxwblfxntth4oy3bfwigv6hw":["inkedjax","Ink/jax/vikt"],
"7vyabeen5tqbszfye3qul54i":["itsviktorryan","Viktor Ryan"],
"6c24nwo5jikjwque7o7rg5by":["jimsane","Jim || Vik"],
"yyymqhnbib4e5bnorwa23dk3":["jonlueke","Dr. Viking Hat"],
"oiksbmj4ki24i6verkium762":["justrandomvika","Vika❄️"],
"qqa732mhmvtf6f4ywdwtoqtp":["jvxta","Viktoriöst Kokett"],
"7tz5gupzcc6moetcn42p5veo":["kahoolaish","Wholesome Viking "],
"yspnbe4ha4xkzbtem3e6n5bz":["kawaiivikki","Vikki 💖"],
"3evxatshgpfldetgj24yotqy":["kannibalkonstrukt","viktor / lucien"],
"x7o7mknrohznpyg2awnaejx7":["katharinaviktoria","Katharina Viktoria Weiß"],
"tgavtlk5763d6o62gggdl7mx":["kloppervictor","Viko versão céu azul"],
"trohurfvdguyzc27jss2nk3b":["kniple","Kosmisk \"ÒwÓ\" Viktor"],
"mmjbjtflwgbhxlyux3q5ml22":["koniushynka","Viktoria"],
"mgfr6cgncvhmh7kfgvmwdppa":["koiwar","KoiWar / Vika"],
"mabeds5lcew2otsvjjrvcldr":["ktorrier","viktorrier"],
"akt7hkv7vxhqicekishfjjo5":["kuker","Vik 🇧🇬🇺🇦🇪🇺"],
"nx5sjyadraeojiupybe3aw4b":["kvl","Vik"],
"tw2uektp4iqcv7e6mo6mepag":["kykaviki","Viki"],
"iwq76ekzcrli66ksfzbg3dhw":["lasrina","Hipster Viking Amy"],
"e6osonmnhfkjlnpqqpu6yj2j":["leviking33","le Viking"],
"actlwivy6usydajagxxha3ca":["leroikimmer","Viktor 🍒"],
"efjj7pzgvsvg44uxv5vtryhe":["littleviking","LittleViking "],
"qxlgjuundoqkddudpiufzwbs":["lisikoff","viktor"],
"dpppvdtewc24ic4hlirnfz7i":["lsktsk","viktoriia"],
"ca7uzjcdhhhmgxe3itkhn7b3":["lsmviktor","Viktor✨️The Karamatsu Boy!¡ "],
"xwji7panedb56q75ezay5s6l":["madvikinggod.com","MadVikingGod "],
"rnjvonvzjzhiksspvvklifni":["mandarin","Thomas Viktil"],
"zpr37jgilxxvmibema27mtag":["marlonlp","Marlon (o viking da shopee)"],
"n3e74adj364xxafga7sx4mjo":["manelsvik","Manels Vik"],
"ii22ikl6vv2lxmerww5aiqmu":["makerviking","MakerViking"],
"sjyed3oh6k236eooiha3vvo2":["marcus5914","Vikas Kapadiya"],
"quaiz7lafeizvjm6pbpjflqc":["machineherald","⭐Viky🍂"],
"ayh4omezagjov2yjdh5ovn6o":["megachecker1","Viktor Schütz "],
"bxccshmlsxihwmespa5v2g2l":["mistereviking","MisterE_Viking"],
"jniein2yw7zyhdksll3pelkk":["mistervicky9","Vikram"],
"a2uwjngd7owq4afhqwzzh5wm":["moonlightdown","Vika 🐑"],
"3yxw54axhpkzibz7irtgduyl":["mrblackjunior","Viktor Chornyi"],
"d4ozzl5amydpyri2ytzhbbyu":["muffinvikingart","MuffinViking - Artist "],
"djmqyu36dur5xzbzuttun7gd":["naivik","NaiVik"],
"kttc23feu7flzgt3dmrtbwly":["necrovalley","viktor 🖤"],
"n6ge5xnbfcbj7cqv6prlysmw":["neimango","Vika"],
"ox3h5flvsb6jfpf6lqnrx4t3":["nicotivik","Vik"],
"ihbwoavbpxw6woqtlnlc6dk7":["nilufer-vik","Nilufer_Vik"],
"6supk3atx57xbsqgb7f7pvem":["nika-viktoria","Ніка-Вікторія🇺🇦🇹🇼🇬🇪"],
"hmb34flm4xxplt33r6k2rj2e":["nsfwmon","Viktor, however slightly naughty 🔞"],
"vb6kf6qq44tsmtrhipn27x5k":["nyblom.io","Viktor Nyblom"],
"rfcny3x2kffpgjegpjudn7zn":["oarielviktor","Ariel Viktor"],
"34mopmsadvwctiy3dd3uwsx2":["onoshkovi.bluesky.co.ua","Viktoriia Onoshko"],
"5e3hdmkdmzyklwd6yg4zf3j6":["overrated","Viktor"],
"ackzl4ykt3erhq3klqyy2bvm":["p0ltergeist","VIKTOR !!"],
"ez32pj22pyfczdcgsvcc3czh":["pansgrrl","VikkiV"],
"qxgitxumizw5bn3dpbtpjxsu":["pablovikasso","Vikas Munipalle"],
"n5fxcwtsevzgao4mrjylomew":["parkotheviking","Parko The Viking"],
"w4slklczcas7su7ruup7amaj":["paralkarlab","Vikram Paralkar Lab"],
"vomwlagqa62sdf53mcbit5uv":["partlycloudycat","Alestreme Viktora"],
"fynr3h2pfn4y6aem6cszvuxl":["pamplemoussable","Viki"],
"s2kwtu5h3chzwd447zazjtnz":["pambera","Viktoriya "],
"b7y7m3ppcrlvybzn4zpjwkpw":["pardalidae","cuidao no resbalar que viktor se va mojando"],
"l56fohmghjaesq3rzgzwolji":["pgxocolatl","Vik Fearing"],
"d7esim7li6p6sffjvnpckslt":["piwonsattorney"," vik 🎃🕸🧡"],
"qj6mromeagl5sx2qvxvk5eny":["realvikashpatel","Vikash"],
"ait5dsmgk6o35knaf2nblcva":["poesjeinboots","Viking Bella"],
"6yda4hhu7skazgzdlgkkx7fe":["profbigbadwolf","Professor Viktor"],
"om6byzo4q5gcuudrhdnn56pa":["protected","Carlyle Viktor"],
"aoejnprlgi4syarblfbwwult":["priestofberlin","Viktor Weber "],
"kcqa3rl73qe4g67f4xdhthxw":["pumpking0re","vik / viktor 🎃"],
"pvw5jvzoeolkq4jbu5iaiiko":["purpleluzifer","SmokinViking"],
"dpplybxkeioqsjok3n2vlgko":["qnectd","Vikri"],
"ct3diaoyvag2374qliw6ckpg":["quak0r","Viktor"],
"y2ygfxy4vvu6ytij6m63jym3":["rascaloons.dev","viktor"],
"fpumzynicyxyg7nsf24ocvdk":["rakvium","Viktor Rak"],
"o5bvhpafxrsjp7ywhkqce7f5":["raubtier","Viktor_R"],
"5hknqgry6c53vc23rhcw7xbw":["realmundiriki","Viking Comics by Yoav"],
"mtpa3ukcdtylwtgcgzskklns":["realvikas","🍁 VIKAS 🍁"],
"yaayslphykp5asio6i3r5mxb":["reverseflash","Vikram"],
"ofcnjuu5l2s3ops5z4cam5qt":["remonpiero","🍁Viko Falk"],
"xihtmc4prrbjs5eet5jnmkm4":["reaper7677","Reaper_Modern viking"],
"teo2x5kgnpkrsflk65dqzeqg":["rforviktorya","Viktorya "],
"x46yy4hbirl66ndnzeteaqwl":["robertviking","Robert Viking"],
"h2qy6gvuijdtzmkoyeq5fk3r":["robewonkenobi91","Super Viking XII: Escape from New York Extended Cut"],
"rmeotdg4od57meaeiwh2qxs7":["ruuney","Rune Håvik"],
"tazhnpi7ygkz3h7s3db2xj7c":["sad-ghost-guy","Viktor, mist wraith"],
"d5tzngsc6e6hnd5jn5safqp7":["saccharinesylph","Lilly 🧵Viking Time 🧶"],
"xtlbgcdxqphomzxqeir2xii6":["sausel","Sausel - a viking fella 🇧🇻🇩🇪🇺🇦"],
"vyr6j7k6lsqrr73ffj2ais2l":["sayaviking","SayaViking"],
"h737fmqlxltj3olpxwcy4nvp":["sensualstroke","Vik - SensualStroke"],
"6xrpfw5aswfxxn4n7nxii4mb":["searle46","Viking Dad"],
"w7up4apk5sg5myeoovr5mam6":["seattleviking","SeattleViking"],
"5y6mwtuyb2iuwgsaq66c5f22":["serovolkova","Viktoria Serovolkova"],
"5q3t2jf2k5ec4ae5xmpsmaoo":["sissvik","Siss Vik"],
"thogscpz7276fpyo6paja6wy":["sissyvikki","Sissy Vikki"],
"oxxs6qrdk2cyfwstvzpuafbb":["sirvikinggiant","Viking"],
"g75uwiextihukefryei6iyft":["sliptori2017","Viktoria UA🙏🇺🇦❤️"],
"5obcbnjotfkdib7idnyh6ic7":["solomonicvik","Solomonic Vik"],
"mi5v4glnaenfqsp56mp4thth":["solidvikes","Paulie Vikes"],
"72gupqublx6orhzafgqdcigd":["sodbrennenvfl","Vik"],
"zvczamuzhiirh3os5ceskfef":["spookystirfry","Hampus Viklander"],
"wn4oa4ejfjwckhymz233fry6":["sparklysheep","Viki"],
"6uffctp4bt5b4vbt46b4rjtc":["streetcar","vikky "],
"qo74zkgdkok77y7pxldbzbdl":["stadlerviktor","Viktor Stadler"],
"vot6zf4nxhbxdesufxgxtkyq":["strangetechnic","Vik"],
"pxhsdpzjf554x5b4ylcx53bw":["stoweyvik","Vik"],
"vrn4szgmylzqfc2dtne5isdy":["steinsindstein","Viktor"],
"ddpf4xydy3ihoqnp7qwuo3cm":["superman1sdead","STDA|Viking.guy"],
"i5adrmdac5h6734zkcgkoqne":["supportviking","Viking"],
"3xa2zwaahahpoo5r2pskryef":["suitman013","StonedViking013"],
"la6bqh5ir7yszoynvipcvohz":["sunnif","Sunniva Vik"],
"45jaunx6c23rlkadq55xuraz":["synnota","✨Synnota ✨ Your Werewolf Viking From the Future Apocalypse ✨"],
"omywnahahirzn6gysyp6di7b":["sykkelrytter","Geir Viksmo-Slettan"],
"ctw7m6vwf5r6e26puyal7ywq":["tahelg","viktor"],
"jvn43caxzhmcnsei2orv6kqn":["tagtraeumerin","Viktoria"],
"clwr7w2nw3yj37ilykvq7cav":["theplantprof","Vikram Baliga, PhD"],
"rzlxzr3pqgs7yyfptdqfnk3i":["thatgaykobold","Viktor Ryan"],
"wgyuasjqmley2rxfrpjnqyz4":["thevikingkingjay","TheVikingKingJay"],
"rgk6szzn7e3yvcjnjufnsnsh":["thatlewdkobold","Viktor Ryan but Lewder"],
"7pt4b3sf7t3i6bxad357cguc":["thirivikramanr","Vikram"],
"iwhxr26mv6rniwfkzephukoe":["theragingviking","The Raging Viking"],
"cjuqmsrbwlozaeilhgdaufxj":["thomasvik","Thomas Vik"],
"naaae32wyowimfszc6fmqbgk":["thevikingdane","TheVikingDane"],
"u53xdyrnjbfb2knley5zgjoh":["tiwari1","Vikash tiwari"],
"2sassqq5ajzsvh4xd4jrqyh6":["tinyanteatermob","I'm still a viking!"],
"l3ww4fljgumtgmcmdgdkykmp":["tori-music","Viktoria aka tori"],
"lhb6rqosr5t42obbjz2ptpvk":["torviktorsson","Tor Viktorsson"],
"5zk6q6kwr2zmg2hhveqstf4g":["torgunn","Lilly Vik"],
"3apl3qr4ygnlx6xtybqjjpie":["tori2705","vikTORIya.M"],
"ope6kr6uro7ivchvlqewb5sw":["tonbildning","Viktor Carlsson"],
"q3turhdhzzni4zu7xmooxavz":["transviking","The Trans Viking"],
"jt4kbxzmxpjrhhjijqoqsa3s":["tristinsanity","TristinSanity 🔞 Viking Clown (PNGtuber)"],
"nwz4y2rptexkpx7ajudfhqnp":["tsuvik","Vikas SN"],
"n2upky5cedaarxeisgwicqko":["tuliptyun","kyo’s vika⁷"],
"b4ezcmdncdwkhoj5mdqbjl7v":["ultramagnusyaoi","Vik"],
"rdkjt52x3h4z7d56tg7ddrlw":["undeadviking","UndeadViking"],
"kwxzqqgkhim6w5eftmkhkbov":"undercover-viking",
"qjgifbiyehaw2goj67bsckke":["v1g4m1","Vik"],
"qasep3cxhobyvvpebjvpualn":["v1k1ng","Viking"],
"2uy7gi3jsu32hdho6iwofzp7":["v1ktor","Viktor 💙💛"],
"uu75v52pzlywa6i56er3yarl":["vatamaniuk","vik vatamaniuk"],
"slvcxbffvev72ydoimyoj5d2":["vamc1986","Vikki"],
"dzzsa7pomqgnhxihynneex7u":["vallert","Viktoria Allert"],
"oxhrsb7nxhw5gi2mjv36dsfn":["vbl","Viktor"],
"exdlffi7o6nw27lrnc5p3rw2":["vdezwaan","Viktor "],
"lq5dpqdijsaafhnvh3g6xhmg":["vdegeler","Viktoriya Degeler"],
"xuwbw65wbkzinhzesqimujxx":["vdecker","Viktor Decker"],
"zhahp5caqn46nehfetnqg7ky":["vfunk","Viktor Funk"],
"ljp6u6kolmjvrrzivskhl2mo":["vfluft","Dr Viktoriya Fedorchak"],
"hl27uzbmikqn6rmdb2qmguqy":["vgarcy","🎃👻🕸️ Spooky Viking Vicky 🕸️👻🎃"],
"innxj5xmb7n5lu5ohzisin5e":["vgandhi","Vikram"],
"iw7i4c6r5m5ktdrj2nh7kr22":["vgrandell","Viktor"],
"fbaemtavgp3lohp7rka4pxd7":["vhp","Viking House Productions"],
"xvet6chhwo36obynsd3r5rdm":["vholl","Viktor Hollmann"],
"4c67iiipy5d7e72xaqcm35l3":["viklets","Viklets"],
"4ys7krzy35y2b22tghaqhpux":["viktiipunk","𝗩𝗜𝗞! 🔞+"],
"54w7lpd5gw4x3pghpcqtkb2j":["viktorlyons","Viktor L"],
"6khy7mmdwlikyba5c752gri5":["viktoria","Aurora "],
"6xo274js6ywhgftvdmtpmonn":["viksit","viksit"],
"b54mvkefhpwhwjwbfibpgi3p":["viktorasmack","Viktoras Vitor Vito Vi"],
"cbib3ziu4d5vcnyca3xjy7zd":["vikbarreiro","Viktor Barreiro"],
"e4xalbv3thmuphljcmytsoiq":["vickyukraine","Viktoriia "],
"efszyrlo7oazf32pycchexyk":["viktory","vik"],
"fscv3rueyovn77fqav6rt2ot":["vikingwolfhimbo","BRANN"],
"fvmy5ddqq7yfu6zmsbwsfp5w":["viking88","ᛏВікінгᛉ"],
"fzfiqf4qm7hx5rpfrwgz4bvi":["vikkik88","Vikki"],
"gtw67zdm35ytyqw665d47bmz":["vikros","Vikros"],
"gxv7zbtzuv6kks27rir3onvz":["viktorishere","Prince of Plunder"],
"hxxtz7agbzgzhfafzyzbgxsx":["viktorastril","Viktor Astril"],
"hypavyk7nkhsb2xzv6jqauvq":"vikeliyan",
"i4vgkmmjdusii5f367bujgwa":["vikahonest","tse pozhezha"],
"ihimkwsqd3fvy4dsznjgjmqp":["vikingr","King Olaf of Ireland 👑🇮🇪🏳️‍🌈"],
"itanmrvzdfdxed5fo2lwh2pi":["vikcleonaturin","Vik (CleoNaturin)"],
"iuttkbpi72kqkwlwj5ufi4l3":["vikamarkouskaya","Vika Markouskaya"],
"ivh5jc7seiiffwz6lwlsfw6m":["viktorshtrum","'viktor shtrum'"],
"jmhscbbqqnynpki3zvnvginp":["vikrambath","Vikram Bath"],
"jpuyav5crq6phha5xgzjze2r":["vikyautumn","пригоди зі смаком коли"],
"kkpphlpo6zkk5dgpxhqgjpje":["vikingyp","YPViking "],
"kpmd2qwjwo7fvuymm7hpxakm":["vikingirishgoddess","VikingIrishGoddess"],
"ksbkbqxowc5mppy4dmhr4zsg":["viktoriablondal","Viktoría Blöndal"],
"ktuvz3zs3klt34kjzbewr5fy":["vikinglass","Viking_Lass"],
"lcxuixnxfj3fp5qd5vlg3sda":["viktorwerk","Chá de Rivotril"],
"lfdaqlfxax5tk6jn6bghprtp":["viktorscoffin","Viktor 🦈"],
"m7bhgmuytvzgjtl6scucjffe":["vikinginrasht","وایکینگ رشتی"],
"m7rnnaky5zzvf4njf3zljpmf":["vikingvrouwe","Marya 🧶"],
"nm422yyceorjzc7uqsrfentq":["vikhyena","Vik: Hyena Hole θΔ ➡️ Denfur"],
"nrmnoz7kidnjxqwxvl3srw6h":["vikki","vikki"],
"o3ujram7azeofcqkqddcjz37":["villagewitch","vika "],
"o56pavckrnkbundbdfx6ddfi":["viktosha","Перемога 🇺🇦"],
"o5exgt6gniampdauygxutzq7":["viktorwinetrout","Viktor Winetrout"],
"okhbetthdm2df6vtqw2oudm3":["viktormon","Viktor Engholm "],
"os7dz7vq6q3ktegwszwtj4nf":["viktoriakeller","Viktoria Keller"],
"pcsbdqwxlbsef3htp3au3t65":["vikingrrl69","S. Freyjasdóttir"],
"pfkor4dmz6uqzo35ucf4okvr":["vikrantkamble","Vikrant Kamble"],
"phzor5jejnz7mncad3nif6zu":["viktorkrylmark","Viktor"],
"pyhpj3ozuq3f7zcfubw6xr5q":["vikibamboni","𝖛𝖎𝖐𝖎 𝖘𝖎𝖑𝖑𝖞𝖛𝖆𝖓𝖎"],
"pzhje3ftp35trbhfylrtzk6v":["vikingfuneral","ᛏᛟᛗ"],
"q3gxja4tgdkde4b4yadhf4bv":["viktorfrontend","Віктор"],
"r3jgswgutwgymrawn7tt57k5":["vikfourn","🔞Public Universal JOIfriend "],
"rdmy6z6gant35o34b7dfdbml":["vikkysrosenmond","Anna Victoria Rose"],
"rglt5l4pqule67uchta36nlf":["viktormachado","Vítor Machado"],
"s6czedgjven7l56njud2bpqp":["viria13","vika 🌿🇺🇦"],
"sc5ycbslpdi6zcafmylsfwnk":["vilya","Viktoria"],
"sceyuhotrzdktg54vt37emyq":["vikhop","Vikhop Bunny "],
"tfbr6wchwbleauiwgiffmqpn":["vikiichi","Vikiichi"],
"tk77cx5kltjl65y3656f4rnz":["vikrant","Vikrant Guleria"],
"tnzf7fwjdveec45ygkrmrrzq":["vika-floyd.ukr.blue","ЗСУ will destroy you"],
"utxgfcsoik6jsrj2t3j7kmrl":["viktoriaidk","Gardentoria the gay"],
"vbljw6ixomhjotaeunomjn22":["vikkiabby","Vikki the Bag Lady"],
"wxkuangneax2vr643l4tgghc":["vikfrogboy","Vik | Kei"],
"ycegpyxsiyggbmqbusfipauz":["vikbm","Vik"],
"yr4awyghqmmk2kb6jxrxpist":["viktordimitri","Viktor Dimitri"],
"ytoq2ufioilozuinsd57qshq":["vikes","vikes 🙇🏻‍♀️"],
"z33wdzrmgki6lmtabj27hssg":["victor-tokarev","Viktor Tokariev 🇺🇦"],
"yrotnpdegh7pazu3j73ymqzy":"vikrambhai",
"nh3msdd5uqarxrhkjm4zsa63":["viksharma","Vik Sharma"],
"wdtqmswncrs3v7fws7i4kfqs":["vikings","Minnesota Vikings"],
"fzefld6ver7jzecvfucvyxe5":["vik","Viktor Krč"],
"mab3iltjmfnc7qpyoji5yyte":"viking",
"7ubtrdpztykcjz72bkdzzqvx":["vikram","Vik"],
"whxaktwgprzwwo5w6k5tepwe":["viktormayrin","Viktor"],
"4fdw7bselveuwkdp52a6n2gu":["viktor","Victor"],
"p7wbeqbwbmsablei4qfafe5w":["viktoriia","viktoriia "],
"xy5mbtbrx4u5pflkq4xuyoe5":["vikkie","Victoria M. Walker"],
"nk3qzsm4quv7qybq52waxryp":["viksaraf","Vik Saraf"],
"6ekqrpzktfejuh2ynb6cmicd":["vikas","vik"],
"kxs3szgjhtbpo36h2i7kkcwu":"vikase",
"ox6rmsfftberk3jm3j3zktba":["vikramk","Vikram K."],
"gjiler74w6kyeygaw25nzugk":["viki","victoria"],
"7tk6beszf64c6bdkgfkegav5":"vikster2k",
"hmuzsgxpu3edzodtqqb6tjbt":["vikramesh","Vikram Ramesh"],
"fgheqwqhajo3oy6bglnkpo6l":["vikvicariously","Viktorija Mickute"],
"z2lkz45tb5uuukvmpoo2x3mm":["vikashsingh","VKSUTD"],
"chhotxuosl22vk5vfkpgdrh3":["vikrantsc","Vikrant"],
"zmhcenoyqcqqdmcdtwizkecq":["vikkibitsyspider","Lana Del Rhaenys"],
"wxxncgmzmgduyr76qff53ylz":["vikkis","vikki"],
"ckgnwtuveundbxnzn5hrby4o":"vikingqueen",
"llrzew4vtwe6obmnniondu5m":["vikrama","Vik"],
"tiftxysitjawuaug4srdumir":["vikke","MATSUNAGA Ichiro"],
"mnpa6vlkijvyrl6gk3iwdbfv":["vikster","Vik"],
"gup3tamj5ylm4s7my6tdec55":["viktoriya","Viktoriya Shuklina"],
"5zmnhqlectis4gsqqe3zgezj":["vikanezrimaya.xyz","Vika Shleina 🏳️‍⚧️"],
"ipl24h77f5bek4dpgeynimqf":["vikxx","vikxx."],
"wk53qluijzizbkqesexzxboa":["vikonstanti","VIKONSTANTI "],
"of4d36vqawwb6sdgigig3ifn":["victoroge","Vikthor"],
"ipyp734ngpxf4v56pqq73bge":["vickypav","Viktoria Pavlenko"],
"apw7mup4zmmf6n2mwk353wdg":"vikasgorur",
"4fo5zjet2ei4kkk6y67ovh27":"viktordolishny",
"nak64lxzzxzyy7yajf3dvshb":["vikinggoat","VikingGoat "],
"nxxmol653l62hnzx3i6gdtod":"vikasmenon",
"5owzwos76kwo2llzjh3squof":"vikmeta",
"7ohpeowcotsktpe27vvq5ysc":"vikbharati",
"76w6qpync4xqlkw2na7goehq":["victdim","Viktor Dimas"],
"rbxo2sooci5vsg2rgkotgifh":["vikasnag","Vikas Madhav Nagarajan "],
"pwhojhvtjoyuui22jcvhpgde":["vikhyat.net","vik / λh.(h h)"],
"5v72rmhahm4ucudp26bbted2":["vikanes","Paul Morten Vikanes"],
"2xc6z7tqs5ribvgqbr2fmbdr":["viktoriyazh","Viktoriya"],
"fp6o3t4zddmq5rgkwo3rarij":["vikkink","molecular vernacular"],
"s2ucgncmeamzcu7fwxjsa4tk":["viktorzub","Я Віктор Заза"],
"dvjvzs2hxynzh3g6y6cicra3":"vika",
"c4b23zlcj5cb5pr3nk2fku7e":"vika1972d",
"pgbijmttmpnuu34rg4br2rkx":["viktor343","Viktor Malieichyk"],
"pw3ctymof7seume6kqby66w5":["viktorv","Viktor Valgarðsson"],
"sdjrtw4livfqxphwzba6c4a6":["viktoriacz","Viktória Rácz"],
"gcwoj7dlzwsa47w6lqxz5txi":["vikintor","Vikintor"],
"36kmbgk7mto2hxo5ljvobvu7":"viki7",
"btqahydeyffwqovjr442exwf":["vikvinegar","Vic Vinegar"],
"t3emhjdewrdxel4eoarwwjpb":"viktorrr25",
"pqxenukczudk2fbdy3cciehq":["viktorklang","Lgd. Viktor Klang"],
"qxy6wgcdsrwsfefzl5fmmlqs":["viktormaruna.com","Viktor Maruna"],
"yhm2vxyyncw6hpb7amawillh":["vikkiberetta","•VIKKI•B€R€TTA• 🎙️&🎬"],
"j5ukzf36dchuwuveikrfcmkt":"vikingo",
"5ellhyzh65xl7vswbhuetc6o":["vikttu","Homer (fujoshi)"],
"z4pki3ipgzv2jwjkfj7dw4yf":["vikingsl","Viking SL"],
"cuzumsaxwyjuakjs3fechamk":["vik.lol","Vic"],
"dchcbupwdbqzmwxpvtv56xkj":["vikrammohanty","Vikram Mohanty"],
"4lxwmco3z4d4ut4vfyvawptl":"viktoroptimal",
"epunbo4rkisdbrr345wku543":["vikk","Vikk’s"],
"tlea3ftycihefadefqxlcawd":["vikuromi","Vic"],
"6asesqzxkhn7pegsqmcnl3p7":["vihluzitano","Viku"],
"os4yhsioljddywgavu3zv6it":["vikingtower","Viking Tower "],
"n7225ftr2p26cclngaizllqq":["vikalp.me","Vikalp"],
"dln3kelxhlg5vcex7u3onqjl":["viktorminyard","𝑣𝑖𝑘𝑡𝑜𝑟"],
"tvv4kw23x5m3vegwbq7zwgfp":["vikingjesus","Viking Jesus"],
"jib2vocke7d74mw7az7fz6km":"viktorious",
"v4b3bsogtt4735k3oiwf75od":["vikingdad278","Kevin McAllister"],
"sj5c24v4mcxzz7rgkc46j3ja":"vikinggoddess",
"mdejv56u46umey5xallqu7ej":["vikingoncall","G. DeYoung"],
"rn2roo2rxgu7n4geyzre47tx":["vikinglady","Maria Loving Life"],
"udbxg5iryikqfkgrwi2vxdal":["vikohusky","Vikooooo"],
"y3jrjhyyvltibis76pr7zt7h":["vikab","Victoria BABEnko"],
"qvu3fxnpf7dsnfbnx4pn3yp6":["viktors2","바바"],
"potyzwytyc6wr5wfy5k5u6bp":"vikrantburde",
"y7rnb253iupmni6axwsilpy2":["vikala","cindy 🐁"],
"zavr7g2gkvgo25eiixeuukeo":["vikingmermaid","Kiley Eberhard"],
"u3ugsvshqim34p5pjxl5d4hg":["vikkimeow","VikkiMeowster"],
"xdpgj6vjeircjww75ir4yzav":["vik0214","Viktoria "],
"sa7nevirz5ls7sbb3xpcgf5g":"vikingking",
"si7moao7rbzwulhd2s4sliba":["vikramnarayan","Vikram Narayan MD"],
"keg2muhdw4rokctk34x4ye6g":["viktork","VikTheDick"],
"vwpvx6shajhh2ssdmugca2nm":"vikramn",
"i4yzoabuxqasbl47sfbkrxd5":["vikingrainbro","Emotional Support Demon ⚔️👹"],
"brjrpfef7izwqugeougaejwq":["viktormaletych","Viktor Maletych "],
"a7cjzcbj4w7bebq5vsjwa6wr":"vikingbrent",
"7bjobantzv3qvrbd34bg3fsb":"viktors322",
"laid4xnci6c2xdb6m6yu4agp":"vikkiread",
"sqkfubw44cropcpeayoenz6s":["viktor0r","Viktor0R🔞"],
"x3qaqpo5onpxsxzyn7n6ewon":["viko","Vīpīn Kohlī"],
"ings5bl3z6bkosmeg4dvrwnp":"viktorbelay",
"p7g6xvitp7yzxljngyixxj7l":["viktorms","Viktor Mayer-Schoenberger"],
"tiuu55rjdv4mj4gdwldbyuf6":"vikki2k",
"jdmsl4e42i2td5iht6352il2":["vikilovesfacs","Viki Male"],
"zghpkrfzlqtp2n4ovc5fcgbd":"vikt-or",
"sapikdu2z4y5rhmzyguwehyl":["vikkipatis","Vikki Patis "],
"yhwpfmaoep4ydbnkorpymw2t":["vikachu","👑Queen Vika 🖤💖"],
"bnhjsvmmf7nbzswm3kctffrb":"viktorhaag",
"nwccrkpyxtjldjbxra4rfrjl":"viks",
"tyb5j4u7vhhrkxbj3lwdho56":["vikafirsss","vıкa (taylor's version)🩷"],
"7bgouffe2cqoqax3slhll47o":["vikayaremko","пацючка оперативного реагування "],
"4sg3ck7pu7oqvgrnoq3dztrq":"viktorgab",
"jonz2krnkr2h35vw7gagkgal":["vikingwitch","Viking Witch"],
"jlycedzjw5dic46oqufm5dad":["viktorsml","Victor"],
"6qkfoczkvk5v27dgxbl2rgqp":"vikkidevine",
"jfm7gjocbt7gymv2qmroj4gs":"vikramsk",
"pgg2yh7xkzf44mwpcqbmlwjs":"viktorshamal",
"vk3pz3y5dn4y5qe6242pb66a":["vik.fursdays.org","Vik the Rebel 🔜 MFF"],
"2mprchnuwnib375bate5crb2":"vikingx",
"gdqt4leylf7wdcuqecc3eoda":"vikgulati",
"4d2hn7faexqy7b4h65q5ne4h":["vikingguitar","Viking Guitar Productions"],
"a2xluy2ayia75mqj7ujckka2":"viktoramenti",
"zqn2xh7icte3xbggid6agklk":["vikingstats","Vikingstatistikk"],
"b2ghcodt72rtt4h6esgbwgvz":["vika-vikusya","Vikusya💙💛"],
"6swvpyhlzhwvxmrle6v6umv2":["vik44","Vik44 "],
"bvq5yppowzbmc2d2tmjlxzbo":["viktordevonne","Viktor Devonne"],
"r6n3pfngh4lo7e6wbierbqsk":["vikkiwrites","Vikki Writes"],
"vjdfevpijqldbrhegn3lmp2k":["vikta","Vikta"],
"s7nm2pie4rkwf6hjofrlj3zs":"viksvaporvub",
"lm6ms32dncpxpifsxvo2ixjn":["vikos","Vikos"],
"fzailfgfsf77lrzvutgvxv6d":"vikabit",
"juruhsn3a76z6b5zbh6c73xu":"vikingthelast",
"7gxzxhycu2xhkggejvfwntcc":"viktoiraomi",
"5cuuvweqvaygpxdtt3aaxbub":["viktorius","Vitor Etcheverry"],
"tflk4pywpw6cjpj6i336cca6":"viktor03",
"3lf64bycgpl66fbx3fln664c":["vikingnerd","VikingNerd"],
"frztd5wua7lq4texn5o2g7o2":["viktur","Viktur "],
"jhg32hawvtawbkow4nweoyeo":"viktowo",
"cvfcpasby2gvaoavjepirlps":"vikramp",
"mryxq5323qsoxqcm4tcy6jse":["vikerry","Kerry Adrienne"],
"zexhkx5qmorcy7efc27osdo5":"vikaassohal",
"pge7cqvojmyer5jq2bzploio":"vikkireals",
"2wwo5fi3nbmukow2farbs332":["vika100sl","VikaSL"],
"7f7xq5daixm525uxv3izy3e2":"vikari",
"ibmo2smrseigbtrti5gnaji7":"vikingray",
"msogfnesa6t7ejjumc27bgsa":["viken","RUNE VIKEN"],
"4pgo2sxgkuelznumbrna2fdt":["vikmor","вікторія🇺🇦"],
"ivkchodiy2khuyot2nou5tf5":"vikinick",
"aj64fbm4v3i22of6547g5m4h":["vikasirko","Віка Сірко"],
"zekv2usubyan3pkbmerqtiyd":["viktortalon","Viktor Talon"],
"hak4b3exxdwlkuwxirpk5xmb":["viktors","Viktor Serebrennikov"],
"mhx75lpkdvbvc4oc6cedhtfs":["vikkio","vikkio"],
"onzkw3tsrt46qcjfh2lcla6o":["vikku","Vikku"],
"empsqez6shtxehwz62z57cty":"viktoraki83",
"w6qfyo5j4loerpb4kltfy532":["vikingraze","Raze"],
"feu6755na4dulqgg5jefwbi3":["vikiqnerdballs","Victoria Q Nerdballs"],
"reghwqonfkmq44meb4iyyqt3":"vikramcse",
"ovth37otf6pkba62fqfpjkm2":"vikingnaya",
"baev7nlmxesr3w4uwdtagkof":["vikramsundar","Vikram Sundar"],
"7ksnkybbuqmos4sds2m3g5jl":["viktthor","Vikttor"],
"y7kthg6y6tra4rhmvztuuvom":["vikwest","Vik West"],
"6hqexwfdxibnvazb3s2fs6tu":"viksoyboi",
"lq25vurkzaswyogaztgxtcoa":["vikachobot","Хронічна Лють"],
"7l2kkmlp2py3k5oqfdarao64":"vikash",
"ez75uwqzy23q6wv6pxo6bzkr":"vikingsson",
"lhujeymejux247pzuupbjj6g":["viktuhugo","Viktu"],
"vz5lhsasvwhjars5yizn6tcm":"vikasreddy",
"3cec4iffl6qzyooiwyuimyww":["vikinghunter79","TravJenJunkie79"],
"vowxcxq7gzzfar2riosiro2v":"vikingjen",
"hs54vya34iyxslrvtaamalz3":["viqtor4yk","Viktor"],
"ybdkesbuo7ybteswskci2u2r":["vikayarova","Vika Yarova"],
"phbbl3oi5ei6c3k2sp3zn553":["viknotbic","#🎃VikMalo 🏳️‍🌈🍂"],
"lt5dhwh5e2fo5sk2fdztve6p":["vikky","vikky ♡"],
"te2v4dvo3jo4wikuoivotgvo":["viktorf","Viktor F"],
"ysvsuhyasqetafnfi4t5si6i":["vikenw","Viken"],
"uyzgcz4j3dyurbrekoefcjm6":"vikalp",
"yq6qvopx6sq2pfqggmomclkz":"viktormizer",
"3pjdphsfiumlilrgaowoos7r":["viktorz","Viktor Zahtila"],
"rio3sviynhawdoywgi2ctkvi":["vikvimes","lemon tektonics."],
"66ow2aru6xygpjzly5hcrn43":"vikasvasudeva",
"52u3gndee7pb2wajba4qol7v":["vikramkam","Vikram K"],
"i7didblutkoh6lbgkiu5irhr":["vikkatherobot","V.I.K.K.A."],
"f54napg5eonol3ojm4wiq2jt":["vikkk","viktor ⚧"],
"7p4w5ggo6diwpstjtasjbexa":["vikivice","Viki Vice ⛓️ Chicago"],
"me66brfrlcy2b6pmwa2nfl46":["viktoriiastep","🇺🇦Алчевська Бандерівка🇺🇦"],
"y5a6fuyrmzukbw3ucxvjgtxa":["viktorjr","Viktor JR "],
"wtqfgikgcz52zmiiqucsjsqi":["viktorija","Viktorija"],
"3rgbosdxnleq4nvuqu5hoifq":["viktormoiseich","Непопулярні думки "],
"hcnbl7cfx66ky77xyxq3l6n2":"vikil",
"sap6tcoezviscrwtjbbtcppt":["vikkisparks","Vikki Sparks"],
"3iyzd6xh5whgzb242f4gar7x":["viktormaru","Viktor Maru"],
"zokwjtn3bq2dlpoo5fngxlaz":["viku","; 風花viku"],
"lsvm4h6annq2zxmymrnjqe6m":["vickysanctus","Viktoria \"Vicky\" Sanctus - EN Vtuber"],
"inspei52wmvwkosw3xf46hn7":["vikros2","Vikros SFW (inactive)"],
"r2cz2fiufz3lwbtoh6nugd4i":["viksunflower","віка з квіткових "],
"rfuydz4rffsdnveucnxqhlaj":["viktorschafer","Viktor Leopard"],
"p7v7mbwqnt7a7x3cg63flh4p":["viktony","Viktony"],
"o3435nio6erzevm3klelnixv":"vikkilea",
"y3tcjzzu3cajc7tbgciii66j":["viktorcrane","Viktor"],
"nuqzcqg5vnplvu2ftubs5uqp":"vikramgopali",
"mspewiiokaaqn46q7l2xrac6":"vikeshavius",
"uvposxxtne55b3pzccrmvp55":"vikines2002",
"rsqcs47hommmjx6c3k6u4rpf":["vikramarora","Markiv"],
"k3gnvt3koeklfxp4c4jxjkot":["viktorjlara","Viktor J Lara"],
"erah3z6l243624dt254t5eyv":["viktorsairano","Roland Deschain"],
"4mddsosxpgiomkxfb55ahkex":["vikingkvinde","Viking Kvinde"],
"4atngqn7fqiiujap2uqyvrdv":["vitiv","Viktor"],
"n2ne5vdkflzu24ewdvorka4w":["viktorhope","Viktor"],
"ztjlgmhyrggennjuw4ku45ak":["vik5y","Viky"],
"3mufdzaqr6j2vmdqk2gy7dg4":"viktorwallin",
"4sqrrckzvknxu23wqsle5fby":"vikua",
"332bipgf5prqndxgatipmzcn":"vikkikaran",
"gvmwrefz22wsts64b2ftmysn":["vikrantkaushal","Vikrant Kaushal "],
"f64jrci335inxgifkwwfr53f":"viktorbo",
"ks6w63nsjl6xbypffiimltxk":"viktorkektor",
"vbiiql7d3bjrjlp6ymdxnerz":"viktor-ig",
"yxi4uqqjzjc6ztluv4l4d53g":["viktor-honey","Yushchenko Yes!"],
"fwzeq4dtu25zhykxfqtdxg5q":"vikingmac6547",
"scmn6wulq3bbi4dvoka23ijx":["vikkothekitsune","Vikko And Lunar!"],
"qjmotk6viiridlocnrwhtnac":"viktorkreiss",
"vd2c2pjbzhe6pmlo2zpsvmcy":["viktorguilherme","Viktor Guilherme"],
"klabh5kttg3d6gilg53upned":["viktorrosa","Viktor De Rosa💕♻️💡🔋💡"],
"qxr6vsnshqhxjuahdrngrnet":["vickylub","Viktoria Lubomski "],
"kyw55oioqauw462yjaonp7b4":["vikingunicorn"," Kierkegaardian Sailor Moon/Chazza"],
"ddjgs6qzagztimmvtjnbpvxr":["vikkitori","🌔💫Нічна Тінь💫🌖"],
"rwhvqayswasskzkvoizta4ta":"vikrantpelia",
"y3kh6ml642fgo4f2vnpwmkex":["vikkurta","vik"],
"qd6jl5ld4hnkll7oebjz2bai":["vividsunsets","vika aka eighthbrothers"],
"pzoynhkulcrvkyrepdjkvwcy":"vikscoggins",
"btyth2bchh7zoz7vdoi7qkm7":"vikraman",
"syodvdgi3t7olmjoamc5o6jd":"vikavolt",
"zmuky77uldyoemj3njmye54m":["vikingolf","Alukard"],
"okt4apizoathyeqzk4u37avf":"viktorseelaender",
"7gvnrhblpepgwih6hwpcf6hc":["vikaspeddu","Vikas Peddu "],
"lfoqtez7zwvwx3oichdvg7vx":["viktordeleski","ViDel"],
"4iakmhdkd2nvhrgzxkb6xbcl":["vikingwolfbrat","BRANN BUT HORNY"],
"xle3zlvvynlfkbjaihifi2q3":["viktorwolf","BrokeJeeper"],
"lr35yt3xvrzhwhnyjvlivqqx":["viktoriavalenzuela","Viktoria"],
"hs7k2fnejynqayxncjr26lmk":"vikkicantrill",
"owv2pboygmjqumkaotbvq5q2":"vikkao",
"yfujceaxzcf5esqquxje7ne2":"vikingsmeisje",
"kexwsaa7akqggfituefr4c7t":["viker","Viker Magma"],
"hvk3guxlwkj3karv23wfkogz":["vike","vichael myers 🔪"],
"6zuyovei2jubgv64vcfjrqnm":["vikingjenn","Ahsoka"],
"kiz47hxf4a4rn3qxvrox3gsc":["vikdreemuvik","Dreemuvik"],
"wsayasllxjwurh6rdjk4i46e":["viktorovna","Olga Nesko"],
"c2hotnnr7ytzv6hbd2zejzhi":["viktoriiazayko","Viktoriia Zaichenko"],
"la4cbpflhtq6piyvw46aoa23":"viktorr",
"xiyexqn2cqhtbht73v4vre5t":["vikobelo","vikobelo"],
"unlbhvnm3pvt4uvxak3jxjzb":["vikingdwarf94","VikingDwarf"],
"a5eskwkwogughjeif446bdow":["vikramchandra","Vikram Chandra"],
"trvc46q7qvzt4zbyvrqpufpx":["vikusyadanilova","Вікуся"],
"vwoyjisvzx6ahjtutoz2m6ob":["vixthestar","Vikki Vix"],
"kq2jxera2arhjiwrlovzx4ff":"vikingschism",
"mdgavmerfnr6tlselgoh4aa2":["vikiss","Бакі ін тренч"],
"sasarb5jid35whfnzhzrnrdm":["vikingbullxxx","Vιƙιɳɠ Bυʅʅ 🐮👨🏻‍🦰🪓"],
"apaflaxxwkdwdl3ep6v4cti2":["viktorvuka","viktorvuka"],
"sdy4mzcxvr5zrjhjdmqze4t7":["vikkidex","Vikkidex 🇭🇷 🇪🇺 🌻"],
"w7fce2bxe2ekl5bvqyrfzwpy":["vikingphotoyork","The Viking "],
"ip5gnmxouaned4qkjtlptvie":["viktornd","Viktor Dezinova"],
"zz6vzurwetbsoa455eajxsz2":["vikburgi","Viktor Burgi"],
"mwnmunvkkbrzrc7zq4peqxnl":["viktorhyenafur","Viktor Lozano"],
"mloh3wt7e552jowtjmtogumw":["viky","🌸 Viky 🌸 Artist"],
"llr5dqnnygb4j6yiwce3tojt":["vikareus","Vikareus "],
"gqwfje74yvq47fjc4erity7j":"vikarna",
"vmslqbdb2gcf34fulfctu3op":["vikracki","Bies 🇺🇦"],
"z4vhlbebfjkxylv7mqvtfu33":["vikraal","Vikraal"],
"fodwrsq2shmkzhakgwltky7h":["vikaezhevika1","VikaEzhevika1 "],
"fsvggcpmb7mnqcbcwrgcenon":["vikschum","@vikschum"],
"6s6xv6lznfg7cpafxrtsuic6":["vikasnavaratna","Vikas Navratna "],
"fi4oolercva7awt5kuj2jag6":["vikvampyrus","Vik Vampyrus"],
"m6twzx533s7hs3i3jw56fgwk":["viktorst","Виктор (Старый)"],
"exkg45iq7s6a2uqfd4l5dsxo":["viktorbb","Viktor BB"],
"3vmrnvocy5ytzupehzmsk7qy":["vikkiosu","Vikki Osu"],
"riauyjx67ghssy2yc4qnrj44":"viktorkropyvny",
"7q2ngzjmbwkbihrcfjfqcvug":"viku-k",
"6mk3mh72pdtuotc67dxxx6u3":["vikki-emma","Vikki"],
"rosnhuq6tkhr5siffhbkpxc4":["viktor-vasyliev","Viktor Vasyliev"],
"tiutkpp27ijskaqxb43nnwin":["vikingw","Viking Waldén"],
"kalvemu4mvhax6n5gbxpbi6k":["vikinomija","vikidor"],
"xufubfo2br4jmrtddnbfimwl":["viktorred","Viktor red 🔥🔥"],
"fh67ebd33czwxnkhg7qd4dbb":["vickypedia","Viktoria "],
"2yt55iazjbrbrayoxfxtqhhh":["vikukapsiholog","Вика"],
"jr2cjs5zxne6dp2bb7szegbw":["vikingaethelwulf","Æthelwulf"],
"3ra2ma4aoprfjn3wqeyjpexw":"viktor92",
"yicsakmzqld72xo2md5tdyel":["viktorgremory","Viktor Gremory"],
"eldtnrnzvxavxcbxczlvjzeq":["vikingsvssamurai","vikingsvssamurai"],
"7h3362zd66wrvximffio7rzp":"viktorbezic",
"56wrgaqisa5oyvzs4o7fkc3q":"viktorrkraus",
"ucoi3v3pdn52wq7h6mmh2yrc":["viktuuri0nice","TheGirlWhoRidesLikeASamurai 🌻💙⛸️"],
"azhsl6cqz7oe6cjpjf6xx7q7":"vikyurevych",
"hyujsgfp5pdmsv7uf3ka46jm":["viktorhumus","𝚅𝚒𝚔𝚝𝚘𝚛"],
"h2az2regnlqhg72rqmsw4jhg":"vikiskull",
"oodakupon3exykgsrivyyjwm":["vikkl","??"],
"5t4cl3g7uheasqguspswtwd3":["vikg","Vik G."],
"i3cw3s5bi3iwvahdg45cb7kj":["vikingdiesel","Ryan"],
"jyb6ksghpx6iz25r62rnde45":["vikingthewolf","Viking wuff"],
"yzkjjf2lrkk4zkmkccsrk3tf":["vikingraven78","VikingRaven"],
"jtvak756t2dqyg6doelyycxl":["vikyuta","can call me vik (๑ˊ▽ˋ๑)"],
"f6lp7s3s62yoelxq6lvxcm36":["viking13","TheViking"],
"n6uoznwovn5wjibslzmjhja4":"viktortriumph",
"hqx3uecfi4auf5nisk7k2oxj":"vikingcommando",
"5w2dhpmf3s6zul2q5gvgoulz":["vikensy","Vikensy "],
"j6fgrocmickciiyqqpzmckef":["viktorhugo","ViktorHugo"],
"pk2sryv5m2khh3l7n7utm5h6":["viktormarinov","Viktor Marinov"],
"6fxvqum25umc2sypcqnoeade":"viktoriiaeleven",
"eytymzmmyrztwyrl3lx3t3n4":"viktorien",
"632t7xf3oyrlayunxq6smmqt":["viktorvyn","Viktor"],
"6vezcdwqrzsgeg3mavhgs2g5":"vikudza",
"j3r4hyz72dpf4sl7owbnoiq5":"vikroe",
"fauwh4nmutbaedidlcqihznd":"vikashgayah",
"rdjr6tvzkk2yjpfglqk3wexz":["viktoriabolmer","Viktoria Bolmer"],
"tgnqdj7odtbf6otgaphsprx4":["viktoriamori","Viktoria Morasch"],
"dnbqbemdz2aeiqlb5hnfeuzh":["vikingprincess","Viking Princess"],
"x7qyqpdmtpu2ov3wrb2i3nap":["viki123","Viki123💉💉💉💉🤒💉🤒💉"],
"texzj5g6hmd5x5mtpsfxag2m":["viktoriawaldegger","Viktoria Waldegger"],
"4gladm25xq54nwuwv5dkpelo":"vikiuniicorn",
"6m5xcrrijfgs2yqtvxtxcvhc":["viktoriyalimbach","Viktoriya Limbach "],
"vm2bunf2fvw5ox63kqnwgfel":["vitrusia","viktoriya f. "],
"tu44guf2j6ov57tacufukgyk":"viktoroficial",
"4s4hptsgcuzmguinf7ulozmv":["vikingbohman","Viking Bohman"],
"2vtga4jacmv2zxv4x6r4kgqg":["viktorroezer","Viktor Roezer"],
"sq4u755ttxj4f537qrpvaea3":["vikingdogs","Viking Dogs "],
"hl2ws2au6x2zg25ia4qn7lna":"vikrrrr",
"xaxswrockh25cngbpn46ms25":["viky2211","Viky2211"],
"dcruv2lgtdehmb2qzok6xgbe":["vikingcub1","Balian"],
"ciihaurxzkijwk7dazwbgtsm":["vikeburr","Vike"],
"jovxepgnbzxk3qadcl5bv5sj":["vikami","v ▪︎ 🦋"],
"4qx3bfcvy3ifhswk67ha53ac":["vikikis","Vikiki S"],
"pnk6esdjjtrojmfrgotd2p66":["vikmastereternal","Vik Eternal Master "],
"qpgxpk63gib3ym6mpymfte7r":["vikinggeek","Viking Geek"],
"tsokbt2f6yht4ox4j2mp3yww":["viktorbresan","Viktor Brešan"],
"xjhup4yjpwipt2x3kjgushsw":["vikulan","Vikulan Blue"],
"uzzlnshrpldqmngmkg6g5jcn":["vikko","Víkko Suárez Casanova (he/him)"],
"2qol44bnaajr2kheyumd4igg":["vikramsingh","Vikram Singh"],
"3fncmvhmztcov5rrfy7bbjqc":["viktoriakehler","Viktoria Kehler"],
"gcgmdtrkuo2bbz623afwqv2b":"vikkitoriav",
"momvyvjdthodzxuh5725xv7u":["vikkistar","Viktoriia"],
"fkipwk6w3ajhgr5lr3dhbmn4":"viktormk",
"lpefgfm3ju2acpdljbabwkls":["vikingsuns","VikingSuns"],
"uphm6xynwxd45vud6zsaaseu":["viktorgiacobbo","Viktor Giacobbo"],
"g2xinvu6o5ktry6eljnkprql":["vikkikrash","Vicky Roberts"],
"wdqxiwtptx5hnusn6gdeuvtq":"vikyen",
"kz3knr4mwpt3iwe4sw2qjnid":"vikashsarraf",
"jlwewzyrmdbnheuxwonduq6k":["vikinggirl","🦋 Viking Marie ⚔️"],
"pxwzllqzctacx5jx57h36zet":"viktorbobbin",
"etv2dwmqzggz7lgd64pxr2yz":"vikas85",
"iwxeuzd3en7tihkwtveoqnbj":"vikingmac6546",
"ke36qibbdaci4fa5q4z7a33x":["viktau","Vik"],
"7rhhvdg4g4jywp6xuar2yek4":["vikramalva","Vikram Alva"],
"ma3xiuxryusg7yxcmkelzal2":"viktorboss",
"jp6vnkfsjgtxmoevinntnb6h":["viktoriamurskaja.com","Viktoria Murskaja"],
"mcoeawcubea43gmrkje26sh3":["vikratt","VIKRATT"],
"cxmpnnrelfcvcugfaw47cqzg":["vikcia","вікця праклённіца "],
"euwr52iujdi2i4qkzczdcwxs":["viktorsky","Vik"],
"dvqacev6bgesxpwr3uiom2l2":["vikingstid","PUNCHMANS GAYSPORT"],
"7caad62ptivdxds3gzdgsolz":"viktoriginal",
"e3h5xaiqx6kfgvs3sohjisvp":["vikingbull","The Viking Bull"],
"5slngsvffwcsvywtzy7rcy34":["vikkehakkinen","Vikke Häkkinen"],
"ljpvuj47wvvnmsu5mpzv7hxi":["viktoriialpv","куся"],
"h5r4x4izffmov6u6mkxnse2x":["vikentihorse","Викентий"],
"ugqu553aftorq4i6gmk7lu7x":["vikkoandco","Viktor Aarto Bloodhowl"],
"2fnow7itftpn6dfkvtdp2ivr":["vikvice","Vik Vice"],
"572lwep2hvixsvbst35ah5op":["viktorcomc","♦️ V I C T O R ♦️"],
"q47hejwn7manb4cuhymwauwb":["viki-kmf","Viktoria Kamuf"],
"r62tpuxgdaudz5c3ajnjvzrt":["viktorianflint","Vivian"],
"kqkytpsxvl3cv2mnyyb3zfzs":["viktorericson","Viktor Ericson "],
"lkbje43v7lzrbwmq4xzwi6zc":["vik-t-orn","VIK-T-ORN"],
"sstggaxgyf4p2mtzkhivdnax":["vikingarmysc","Viking Army SC"],
"7wmv44l6nn7gg4k5ohomzi3b":["viktorivia","alex"],
"uk4xkm3rskaphayac7uh7fo6":"vikanda",
"z67bxk2k6xajur2b644m335t":["vikingkatz","Luna Viking Katz "],
"dy26jjj2xtklmeunrfn2vepc":["vikasmc","Vikas"],
"lxmwki6pnbgypsgsmx653gca":"vikivia",
"nk2jxvde4erl4vewgd627egb":["vikingfella","Viking Barrister Fella"],
"32xqd5kiw66qoarihyogga4r":["vikatus","vikatus ⛧ 「 SILVIN 」⛧ vtuber/vartist"],
"3xkkqm33sjnh27actwdoxpev":"vikakosiak",
"vwvptrfozyrdzrrzccmy6n2c":["viktorya","Viktorya Muradyan"],
"qsvuxvovczwpq2laoo53bylq":"viktorsbergenholtz",
"tkpx6flpoqfa3mpiax2w4zqc":"vikkan",
"ls2pv3oy3yf3kx654b6r432g":"viktorc",
"mx4rfvxqlj5zy6enbamqkwgc":"viktorwolfdog",
"i2xineu7kesevlvrhifdmft3":["vikav","Vika"],
"jcsh33lu5nflx3shbneu4ysk":["viksocius","Vik"],
"gsk7tdvrcfp6s27qv77g7rtk":["vikatoo","Vika"],
"dswuqzacdsabiwe4xsqmtoog":["vikayurijivna","Pyrizhechok "],
"67ortdcbpaxwja5ty3k5ufxl":["viktorxtsui","viktor"],
"5xibg2emfbng25xpzdphwopv":["vikingtr0n","VikingTr0n"],
"ntatur5jm44nqt3lruzzwc4k":"vikssam",
"vch5nzh6oeigiak2mupf4qyt":"viktorkicktor",
"dwptoofmm6smavsy267erk65":"vikingmac65411",
"5eztd7hnguedlmvb2ykjwxmt":["viktorbk","Viktor Barth-Kron"],
"i3cr5nt4vqijmykxgaqzmocf":"vikshirley",
"dn476c6bb53mqxyjy3pfrodc":"vikkithomp",
"hlz7urmy7jzfkolbqg2tja55":["vikkimikk","vika bibika "],
"tck6mxnbgtriklmpedc5jfjt":["viktorpuss","viktorpuss"],
"7no2cypeqxqc6b6fd2j6elk6":"viktorg",
"ghajygy2zwzbqal5kymdhfmg":["vikashumko","Victoria Shumko"],
"z7swposlkadwks3lrklgq5s2":"vikfed",
"vwg4y4ui4u4x75o3vhjxrytz":"vikkik808",
"3l2bctgnyiitgussilhimzml":["viktorrantala","Viktor Rantala"],
"7fajtpbmcr54w3jxs36mkkwi":["vikkenmusic","VIKKEN"],
"6eppejuupzd4y45xeui64wyk":["viktorfaustva","Viktor Faust"],
"f5lmrolna66jhaokzdioy6bp":["viktorkvachan.ehoss.com","Viktor Kvachan"],
"7eis3nnrkzuh2fuh7uqffkel":["vikyian","Vikyian / Leirofir"],
"ymrbjx5cmwsvte3yb3fzwmnh":["vikitty","kitty"],
"cfbi5azzmv6auuxqthzraw7o":["vikingwoman01","VikingWoman01"],
"ws6gz3wqabgfkgb5vagibty5":["vikysik","Виктория"],
"375a4rixidy6oapiibiufyut":["viktoriareich","Viktoria Reich "],
"qzotplhnc3rrengn3fl5nn2n":["viktoriaauer","Viktoria Auer"],
"kficcqeelqjafr2fmvyry6nt":["vikakiv","Vika"],
"hdyv72iihf5t35d4mprpeopf":["viktorki","Viktor Kippes"],
"zjhfkj34qxasevoj7nn3ok6q":["vikkim","Vikki M"],
"zefc2ye6e6ogp6yojtxy7yvf":["vikingerik","Vikingerik"],
"laad5embby2fev4ttkn6aawz":["viktoriaspaiser","Viktoria Spaiser"],
"kg7vogfeug65mpvqehnewpzr":["vikingfirebug","Máni"],
"rttfnhaschgx6bohglerr7mn":["viskot","Viktor Tullgren"],
"hw5jyifrkhg2mqc62hhxpyxb":["viktormarinkov","Viktor Marinkov"],
"ap734qnndl2sz3agszzsv4u5":["viktorgray","Viktor Gray"],
"nx77q7ay4fetl7b73vn2j7bc":["vikaspotluri123","Vikas Potluri"],
"q2v5g3bbmsbgs7jykd7iafov":["vikesfan33","Kurt Van Thomme"],
"s2kkltc3ctkmpqwq3vq7fytp":"vikingholland",
"it3l3q4jy4xek3ixm3gdst4b":["vikrd","𝓥 𝔦𝔨"],
"ed2sym4aaypkrorxwrrz77ze":["vikathi","Kathi"],
"qv6aae26aoek6vzs2xiao2xt":["viknightfox","Vik Nightfox"],
"jso5f3lewhtamr6m5cjgyfn3":"viktor55",
"gnfeuqxi4enz7g5fz2gczel4":["vikannan","Vishnu Kannan"],
"rf7onvj5yodmaustenn2j2zu":["vikmaksymenko","Viktor Maksymenko "],
"tc6r3lad4vrjwick6ov7ltcm":"vikoooo",
"nzkvzl6hugm2rfh7b7zmgic3":"vikolamenace",
"h2qm2yz66zjxqjbn74ekrx2z":["vikot106","泯默.Vikot"],
"s2n4njdctrhcwnmdmag4nuug":["viktoriapark","Fabian Lang "],
"ewcgopbk2af5hn72ym64svr7":"viktor11",
"z4x6zvrcilaj5turf3a64a5l":["vikingonrails","Aram"],
"7iffxekhgchb4ives5onx3mq":["viktor-k","Viktor K."],
"dfkftpsyb7d4tt67uiczpe52":["vikingwomanglitch","Glitch is training her thighs to crush skulls 💪🏻🏋🏻🍉"],
"epvjmpbx4szfene2ucx5lxuy":["viktorannerl","Viktor 🎞️"],
"74qs3hlktydujjspkdgpn7zb":["vikingoespacial","Vikingo Espacial"],
"asfqx5mjbp4ywn7izh77o6va":"vikrantc",
"trbliivwrqcputhecjcqrm3i":"vikksr",
"yigss3jsk2pcm7ik3nh7qvl6":"vikuletta",
"wqyb3a4ng2wfma5f3fjdscmr":["viktorvaughn","Viktor Vaughn"],
"kgebd4g5easmn3ramqadqxdh":"vikkysula",
"jp6yiwkhxhbz2qirhp43kikl":["vikashkumarahir","Vikash"],
"zjrrbi3362iqz7ug2bkbe6k3":["viktorostling","Viktor Östling"],
"33zyubqipaf2qb4wj7kmhf2k":["vik-ermitage","VIK"],
"z7mjr44puym5omfm6bh52uam":["vji","Viktor"],
"vagqrtkhiivmkgxmitdbx2l2":["vjustov","Viktor Justo Vasquez"],
"4lz2te6jz433cuk2w5vgd4rx":["vladyzhets","Viktor Ladyzhets"],
"kachoyiibnq2ey4piiy6eewu":["voberoi","Vikram Oberoi"],
"aiypx6vrg7pclfahoybjt7p5":["voidviking","🎃VᛟID᛫VIKIᛝ🎃"],
"sohwfibknklxczngmaak6vi5":["vpwell","Viktoriia"],
"fs6ex3o5wj632e4pa6irk6kq":["vray","Viktor"],
"wsjyj33bfq3jknfgxpwr7f5o":["vryvirileviking","🎃VrySpookyViking🎃"],
"25twcc54z5fpxg2kpxahdjrc":["vsaraph","Vikram Saraph λ"],
"7w6lmcn5hk5ys3672alwrffj":["vtkrlndr","Viktor"],
"gjt72fgtn63oeeg7uefa3wgv":["vttoth","Viktor Toth"],
"ppetenmdemv3xnfykt5yolda":["vulgarrviking","The Retro Viking"],
"yx76uehaxlcukkbuyo4hj2a3":["vvolchetskyi","Viktor "],
"f2cfirqhloyubnflyc2w6she":["vvenhorst","Viktor Venhorst"],
"dfrofzsyde3upwlnmsvthqjv":["wanderingviking9","WanderingViking9"],
"4e4spjx3lxyohvu5rlh5rpux":["weivi","Viktoria"],
"pglgmzrbloplfocaybgrr6fl":["wiman","Viktor W"],
"alafx6in6nz2ud6fhp7mptif":["wolfieboy69","Conall the Viking"],
"ycptfdulrz3ot3arlbfwk4bs":["wordsandsuch","Vik"],
"lcrbiyqemrrleoyh4qhxbj5j":["xolomu","Vikki Williams 🔨🏳️‍⚧️"],
"fjmoxikcnuxmxlug55mmugm2":["yadav","Vikash Yadav"],
"7fu234rlozvobmngqe66m4un":["yaoiwizard","viktor (he/it)"],
"kphiusmhpjdvvfw557g5y4tk":["ylostwolfy","Vik🐺 Haikyuu Fanboy🖤🧡"],
"7a3bmcd3a7mosfnyzjpbvh2q":["yuripaws","vik!!!!!!!!!!!!!!!!!!!!!!!"],
"27dvhtdsv666jxm2e2pf5vv5":["zytomega","Vik 🛸"]
}
