{
"gebkbpdiqwocw4hhdahsmxqd":["bram.vleur.nl","Bram"],
"plfbr2q5vh5mb45swqp2cvow":["carmellavv","Carmella Van Vleet"],
"m7l4pmjnnboaonak2zzd4mv6":["cvlessing","Clara Vlessing"],
"ho5adqmtuhfao2zznpqgsfps":["dadevlee","David De Vleeschouwer"],
"sbgcjhkdfwlegg72zu72notk":["jeroenvlek","Jeroen Vlek"],
"7asylv7by644bgqodqo7rhzd":["liesvleugels","Lies Vleugels"],
"ebgyhgsgwduz6mafnxe5fkp6":["maartenvdv","Maarten van der Vleuten"],
"ui2yrvnwljwgyiyvo2ivcg3q":["pomahaceduard","Bůh momentálně ve vleklé válce s ledovými obry-Nevrátili sekačku"],
"t6kt3e2o27dg62cw5lolkpqr":["ronaldv","Ronald v.d. Vleuten"],
"az4z3ubu75hyjozaztfwu5ja":["signalstation","Michael Van Vleet (he/him)"],
"4spsdvfevoio2xbqcjc56jk5":["thetastygarbage.com","Vlemish 𓅊𓅇𓅄"],
"iqc32yx2edg6vp3seqiou2pw":["vglaceon","Vlea 🍰"],
"ztymjstoe4dkwmnf36p46o4w":["vitjavlees","Vitja Vlees"],
"m4iemoho3nytffyplsjpfjfo":["vlederik","MaartenR ✏♟🎲"],
"oqj65y3q564clf3qxgq4nbnh":["vlec.be","Vincent L"],
"uk4k57nsj5stvkguphed7lwl":["vletu4ka","Аннушка"],
"w4q32awi5muxqo4a5tpk4ee4":["vleewalker","Broken Branch "],
"ynbaid6s5w2bso5vykvgehkp":["vleermuis","Marvleermuis"],
"fdv44injeuraaz22e3yihc3v":["vlela","Lela"],
"triwxnbjbex4fca5vhj3i5si":"vleal",
"i2jdhooaz7ern3e2u4jfkk2p":"vleesq",
"tuxu3xe3gy6xxgyfmwsonfpd":"vlexv",
"2vif5uyuvrtviudsvtywv5v7":"vleej",
"6xjvhjfwifbmhbt7bxwmmhnn":["vlex","vlex"],
"52vdukowhe65fqu6rw2ogspa":["vlen","Vlen Puppehface Potatobutt"],
"zl7m3sw3c7fyaozvalgdyvr5":["vlexxz","Velx"],
"x2elygiamvbyhfyti7drse7i":"vleese",
"ozl44khdovpvurhwlwgnrvqp":["vleshkav","oleksii.ko"],
"5zt73magg7ovaxvbuc6pltff":"vleighisme",
"zuv2bri7xozgt6w23stx2vh4":["vlestrade","Lestrade "],
"2iuyq4cy5q7jsqhmvx2miemg":["vlerk","vlerk"],
"na5bgt3whybykcrbui2zkfdu":["vlexxaedral","vlexxaedral"],
"qp34dsdf264gno6usiaypah6":["vlek","Vlek"],
"uczwcbhbnq722tvzezgw2k2w":["vlemos","Victor Lemos "],
"wc4c2dv3xsiipwbhalo6gfot":["vleheny","Vivienne Leheny"],
"d2nzmysm5giwofnzkcpq3ssh":["vleckie","Vleckie"],
"eqaphcqerpxh6nukp5yaboi4":["vlegogo","legostaev"],
"cglxjzag5thnhqvzoptcxbsl":["vleidnaomon","Vleid_Naomon"],
"mgovw3kw4fyhfrfz6apt6sn2":"vleao",
"u4dfbke2udnrv2v3ciocidjz":["vledtapas","Vled Tapas"],
"hx5c7uaufakjkcy4ervobvxc":["vleafnin","vleafnin Twitch"],
"ayz4jx6ibbny4h7glh6knpho":"vlekkievankempen",
"x4xnlwzi4ortnzei3ltqx4zj":"vlemonier",
"x3tsimsxaf66d6hfpmba72on":"vlesk",
"j4e6e6mxq67hzytrciqsu4gz":["vlespez","Valérie Lespez "],
"uwqlkoo4txzvcsmoghyeeytv":"vleo",
"7nrim5oix63lailyah7afcvx":"vlerner",
"n7d4tddmwzqhigcz4qwqquhk":["vlepkaaday","Blazej Kurowski - vlepkaaday"],
"nqx352hwyrdqnexdnuck2z5d":"vlegraet",
"2av6jpag5rkz6ts7u7fv4vp7":["vlenzer","Hugo Schneckerich"],
"h43acatpm63ezlfhr5ec7xma":["vleoleoleo","лєруа "]
}
